sreader/__init__.py
sreader/reader.py
sreader/utils.py
sreader/version.py
tests/__init__.py
sreader-0.0.1.dist-info/LICENSE
sreader-0.0.1.dist-info/METADATA
sreader-0.0.1.dist-info/WHEEL
sreader-0.0.1.dist-info/top_level.txt
sreader-0.0.1.dist-info/RECORD
