Metadata-Version: 2.1
Name: sreader
Version: 0.0.1
Summary: space-reader: Convert any file path into LLM-friendly inputs
Home-page: https://github.com/huangyz0918/space-reader
Download-URL: https://github.com/huangyz0918/space-reader/archive/refs/heads/main.zip
Author: Yizheng Huang, Silin Meng
Author-email: huangyz0918@gmail.com
Keywords: LLM,Large Language Model,data processing,data science
Classifier: Development Status :: 5 - Production/Stable
Classifier: Intended Audience :: Education
Classifier: Intended Audience :: Financial and Insurance Industry
Classifier: Intended Audience :: Science/Research
Classifier: Intended Audience :: Developers
Classifier: Intended Audience :: Information Technology
Classifier: License :: OSI Approved :: Apache Software License
Classifier: Programming Language :: Python :: 3
Classifier: Operating System :: OS Independent
License-File: LICENSE
Requires-Dist: setuptools
